README.txt
buildout.cfg
setup.py
src/iwm/__init__.py
src/iwm.recipe.bebopinstance.egg-info/PKG-INFO
src/iwm.recipe.bebopinstance.egg-info/SOURCES.txt
src/iwm.recipe.bebopinstance.egg-info/dependency_links.txt
src/iwm.recipe.bebopinstance.egg-info/entry_points.txt
src/iwm.recipe.bebopinstance.egg-info/requires.txt
src/iwm.recipe.bebopinstance.egg-info/top_level.txt
src/iwm/recipe/__init__.py
src/iwm/recipe/bebopinstance/README.txt
src/iwm/recipe/bebopinstance/__init__.py
src/iwm/recipe/bebopinstance/ctl.py
src/iwm/recipe/bebopinstance/tests.py
src/iwm/recipe/bebopinstance/zope3scripts.py
