Metadata-Version: 1.0
Name: iwm.recipe.bebopinstance
Version: 0.0.2
Summary: ZC Buildout recipe for defining a Bebop instance
Home-page: http://svn.kmrc.de/projects/devel/iwm.recipe.bebopinstance
Author: Torsten Kurbad
Author-email: t.kurbad@iwm-kmrc.de
License: GPL
Keywords: zope3 bebop buildout name
Platform: UNKNOWN
